libsoundtouch/__init__.py
libsoundtouch/device.py
libsoundtouch/utils.py
libsoundtouch/templates/avt_transport_uri.xml
libsoundtouch-0.8.0.dist-info/DESCRIPTION.rst
libsoundtouch-0.8.0.dist-info/METADATA
libsoundtouch-0.8.0.dist-info/RECORD
libsoundtouch-0.8.0.dist-info/WHEEL
libsoundtouch-0.8.0.dist-info/metadata.json
libsoundtouch-0.8.0.dist-info/top_level.txt
libsoundtouch-0.8.0.dist-info/zip-safe
