Metadata-Version: 1.1
Name: libsoundtouch
Version: 0.8.0
Summary: Bose Soundtouch Python library
Home-page: http://libsoundtouch.readthedocs.io
Author: Charles Blonde
Author-email: charles.blonde@gmail.com
License: Apache License 2.0
Download-URL: https://github.com/CharlesBlonde/libsoundtouch
Keywords: bose,soundtouch
Platform: any
Classifier: Intended Audience :: Developers
Classifier: License :: OSI Approved :: Apache Software License
Classifier: Operating System :: OS Independent
Classifier: Programming Language :: Python :: 3.6
Classifier: Programming Language :: Python :: 3.5
Classifier: Programming Language :: Python :: 3.4
Classifier: Programming Language :: Python :: 2.7
Classifier: Topic :: Software Development :: Libraries
